<?xml version="1.0"?>
<items>
  <its:rules xmlns:its="http://www.w3.org/2005/11/its" version="1.0">
    <its:translateRule selector="//item/@name" translate="yes"/>
    <its:translateRule selector="//item/@description" translate="yes"/>
    <its:translateRule selector="//item/@effect" translate="yes"/>
    <its:translateRule selector="//*" translate="no"/>
  </its:rules>
  <item id="890" image="equipment/head/beaniecopter.png" name="Beanie Copter" description="A funny beanie cap with a spinning propeller." effect="M. Attack +2" type="equip-head" defense="4" weight="20">
    <sprite gender="male">equipment/head/beaniecopter-male.xml</sprite>
    <sprite gender="female">equipment/head/beaniecopter-female.xml</sprite>
  </item>
</items>
